plapi/__init__.py
plapi/string/__init__.py
plapi/string/compression/__init__.py
plapi/string/compression/compression.py
plapi/string/similarity/__init__.py
plapi/string/similarity/basics.py
plapi_string-0.0.11.dist-info/LICENSE
plapi_string-0.0.11.dist-info/METADATA
plapi_string-0.0.11.dist-info/WHEEL
plapi_string-0.0.11.dist-info/top_level.txt
plapi_string-0.0.11.dist-info/RECORD
